{
    "dateString": "reprehenderit voluptates",
    "recipient": {
        "individuals": [
            {
                "firstName": "quia atque et dolorum",
                "lastName": "sed ducimus provident illo voluptatem"
            },
            {
                "firstName": "recusandae dolores",
                "lastName": "est"
            },
            {
                "firstName": "facere modi",
                "lastName": "aut magnam esse"
            }
        ],
        "recipientType": "individuals",
        "contactMethod": {
            "address": [
                "culpa dolore",
                "officiis error est cumque",
                "id eum",
                "optio ut dignissimos",
                "laborum omnis labore"]
        }
    },
    "matter": {
        "matterId": "suscipit magni rerum"
    },
    "sender": "Thomas Bloy",
    "valediction": "sincerely",
    "vendorNames": [
        "et",
        "qui",
        "et omnis",
        "est aperiam"
    ],
    "purchaserNames": [
        "quasi suscipit exercitationem consectetur",
        "officia sapiente",
        "commodi saepe minus rem",
        "accusamus harum facilis velit"
    ],
    "settlementDate": "suscipit"
}